nccl/__init__.py
nccl/_version.py
nccl/bindings/__init__.py
nccl/bindings/cynccl.cpython-310-aarch64-linux-gnu.so
nccl/bindings/cynccl.pxd
nccl/bindings/nccl.cpython-310-aarch64-linux-gnu.so
nccl/bindings/_internal/__init__.py
nccl/bindings/_internal/nccl.cpython-310-aarch64-linux-gnu.so
nccl/bindings/_internal/utils.cpython-310-aarch64-linux-gnu.so
nccl/core/__init__.py
nccl/core/buffer.py
nccl/core/communicator.py
nccl/core/constants.py
nccl/core/cuda.py
nccl/core/group.py
nccl/core/memory.py
nccl/core/resources.py
nccl/core/typing.py
nccl/core/utils.py
nccl/core/interop/__init__.py
nccl/core/interop/cupy.py
nccl/core/interop/torch.py
nccl4py-0.1.1.dist-info/METADATA
nccl4py-0.1.1.dist-info/WHEEL
nccl4py-0.1.1.dist-info/top_level.txt
nccl4py-0.1.1.dist-info/RECORD
nccl4py-0.1.1.dist-info/licenses/LICENSE.txt
